pdf_tools/__init__.py
pdf_tools/server.py
pdf_tools_mcp_server-0.1.0.dist-info/licenses/LICENSE
pdf_tools_mcp_server-0.1.0.dist-info/METADATA
pdf_tools_mcp_server-0.1.0.dist-info/WHEEL
pdf_tools_mcp_server-0.1.0.dist-info/entry_points.txt
pdf_tools_mcp_server-0.1.0.dist-info/top_level.txt
pdf_tools_mcp_server-0.1.0.dist-info/RECORD
