Metadata-Version: 2.4
Name: pdf-tools-mcp-server
Version: 0.1.0
Summary: MCP server for PDF manipulation
Author-email: Your Name <hanwegaltimer@outlook.com>
License-Expression: MIT
Project-URL: Homepage, https://github.com/hanweg/mcp-pdf-tools
Project-URL: Repository, https://github.com/hanweg/mcp-pdf-tools.git
Requires-Python: >=3.13
License-File: LICENSE
Requires-Dist: asyncio>=3.4.3
Requires-Dist: mcp>=1.5.0
Requires-Dist: pypdf2>=3.0.1
Dynamic: license-file
